[

     {    
          "name": " लेखांकन (Accounting) - (Hindi) ",
          "link": "https://appx-wsb-gcp.akamai.net.in/paid_course2/2023-03-23-0.2795730297827326.pdf",
          "logo": "/assets/img/pdf-list-logo.png"
     },
     {    
          "name": " लेखांकन (Accounting) - (English) ",
          "link": "https://appx-wsb-gcp.akamai.net.in/paid_course2/2023-03-23-0.9805325523833999.pdf",
          "logo": "/assets/img/pdf-list-logo.png"
     },
     {    
          "name": " प्रबंध का परिचय - (Hindi & English) ",
          "link": "https://appx-wsb-gcp.akamai.net.in/paid_course2/2023-01-19-0.7085908647632944.pdf",
          "logo": "/assets/img/pdf-list-logo.png"
     },
     {    
          "name": " नियोजन (Planning) - (Hindi) ",
          "link": "https://appx-wsb-gcp.akamai.net.in/paid_course2/2023-01-19-0.1982503242348781.pdf",
          "logo": "/assets/img/pdf-list-logo.png"
     },
     {    
          "name": " नियोजन (Planning) - (English) ",
          "link": "https://appx-wsb-gcp.akamai.net.in/paid_course2/2023-01-19-0.8659271618191422.pdf",
          "logo": "/assets/img/pdf-list-logo.png"
     },
     {    
          "name": " लेखांकन परिचय एवं शब्दावली - (Hindi & English) ",
          "link": "https://appx-wsb-gcp.akamai.net.in/paid_course2/2023-01-19-0.7698229531824266.pdf",
          "logo": "/assets/img/pdf-list-logo.png"
     },
     {    
          "name": " नियुक्तिकरण (Appointment) - (Hindi) ",
          "link": "https://appx-wsb-gcp.akamai.net.in/paid_course2/2023-01-19-0.9071569009457687.pdf",
          "logo": "/assets/img/pdf-list-logo.png"
     },
     {    
          "name": " नियुक्तिकरण (Appointment) - (English) ",
          "link": "https://appx-wsb-gcp.akamai.net.in/paid_course2/2023-01-19-0.9071569009457687.pdf",
          "logo": "/assets/img/pdf-list-logo.png"
     },
     {    
          "name": " नियंत्रण - (Hindi) ",
          "link": "https://appx-wsb-gcp.akamai.net.in/paid_course2/2023-01-19-0.4962769579805304.pdf",
          "logo": "/assets/img/pdf-list-logo.png"
     },
     {    
          "name": " नियंत्रण - (English) ",
          "link": "https://appx-wsb-gcp.akamai.net.in/paid_course2/2023-01-19-0.2970041118476918.pdf",
          "logo": "/assets/img/pdf-list-logo.png"
     },
     {    
          "name": " संगठन Revision - (Hindi) ",
          "link": "https://appx-wsb-gcp.akamai.net.in/paid_course2/2023-01-19-0.5351011414516682.pdf",
          "logo": "/assets/img/pdf-list-logo.png"
     },
     {    
          "name": " संगठन Revision - (English) ",
          "link": "https://appx-wsb-gcp.akamai.net.in/paid_course2/2023-01-19-0.3967198456522858.pdf",
          "logo": "/assets/img/pdf-list-logo.png"
     },
     {    
          "name": " उपभोक्ता संरक्षण (Consumer Protection) - (Hindi) ",
          "link": "https://appx-wsb-gcp.akamai.net.in/paid_course2/2023-03-23-0.16736374296535628.pdf",
          "logo": "/assets/img/pdf-list-logo.png"
     },
     {    
          "name": " उपभोक्ता संरक्षण (Consumer Protection) - (English) ",
          "link": "https://appx-wsb-gcp.akamai.net.in/paid_course2/2023-03-23-0.3928215686283172.pdf",
          "logo": "/assets/img/pdf-list-logo.png"
     },
     {    
          "name": " निर्देशन (Directing) - (Hindi) ",
          "link": "https://appx-wsb-gcp.akamai.net.in/paid_course2/2023-03-23-0.6890798417826836.pdf",
          "logo": "/assets/img/pdf-list-logo.png"
     },
     {    
          "name": " निर्देशन (Directing) - (English) ",
          "link": "https://appx-wsb-gcp.akamai.net.in/paid_course2/2023-03-23-0.40327575621672107.pdf",
          "logo": "/assets/img/pdf-list-logo.png"
     },
     {    
          "name": " लागत लेखांकन (Cost Accounting) - (Hindi) ",
          "link": "https://appx-wsb-gcp.akamai.net.in/paid_course2/2023-03-23-0.5333421645978436.pdf",
          "logo": "/assets/img/pdf-list-logo.png"
     },
     {    
          "name": " लागत लेखांकन (Cost Accounting) - (English) ",
          "link": "https://appx-wsb-gcp.akamai.net.in/paid_course2/2023-03-23-0.663934551152789.pdf",
          "logo": "/assets/img/pdf-list-logo.png"
     },
     {    
          "name": " HRM and CRM - (Hindi) ",
          "link": "https://appx-wsb-gcp.akamai.net.in/paid_course2/2023-03-23-0.2884330060027842.pdf",
          "logo": "/assets/img/pdf-list-logo.png"
     },
     {    
          "name": " HRM and CRM - (English) ",
          "link": "https://appx-wsb-gcp.akamai.net.in/paid_course2/2023-03-23-0.9865375386909203.pdf",
          "logo": "/assets/img/pdf-list-logo.png"
     },
     {    
          "name": " वित्तीय बाजार एवं वित्तीय प्रबंधन - (Hindi) ",
          "link": "https://appx-wsb-gcp.akamai.net.in/paid_course2/2023-03-23-0.3356634203050983.pdf",
          "logo": "/assets/img/pdf-list-logo.png"
     },
     {    
          "name": " वित्तीय बाजार एवं वित्तीय प्रबंधन - (English) ",
          "link": "https://appx-wsb-gcp.akamai.net.in/paid_course2/2023-03-23-0.8127459916089426.pdf",
          "logo": "/assets/img/pdf-list-logo.png"
     },
     {    
          "name": " वित्तीय विपणन (Financial Marketing) - (Hindi) ",
          "link": "https://appx-wsb-gcp.akamai.net.in/paid_course2/2023-03-23-0.7462956752951668.pdf",
          "logo": "/assets/img/pdf-list-logo.png"
     },
     {    
          "name": " वित्तीय विपणन (Financial Marketing) - (English) ",
          "link": "https://appx-wsb-gcp.akamai.net.in/paid_course2/2023-03-23-0.3606154039302263.pdf",
          "logo": "/assets/img/pdf-list-logo.png"
     },
     {    
          "name": " व्यावसायिक नैतिकता (Business Ethics) - (Hindi) ",
          "link": "https://appx-wsb-gcp.akamai.net.in/paid_course2/2023-03-23-0.33010253772190024.pdf",
          "logo": "/assets/img/pdf-list-logo.png"
     },
     {    
          "name": " व्यावसायिक नैतिकता (Business Ethics) - (English) ",
          "link": "https://appx-wsb-gcp.akamai.net.in/paid_course2/2023-03-23-0.8844579090114668.pdf",
          "logo": "/assets/img/pdf-list-logo.png"
     },
     {    
          "name": " व्यावसायिक पर्यावरण (Business Environment) - (Hindi) ",
          "link": "https://appx-wsb-gcp.akamai.net.in/paid_course2/2023-03-23-0.47058573168820184.pdf",
          "logo": "/assets/img/pdf-list-logo.png"
     },
     {    
          "name": " व्यावसायिक पर्यावरण (Business Environment) - (English) ",
          "link": "https://appx-wsb-gcp.akamai.net.in/paid_course2/2023-03-23-0.13105213732259147.pdf",
          "logo": "/assets/img/pdf-list-logo.png"
     }

]